kyzylborda_lib/__init__.py
kyzylborda_lib/generator/__init__.py
kyzylborda_lib/generator/__main__.py
kyzylborda_lib/libc/__init__.py
kyzylborda_lib/sandbox/__init__.py
kyzylborda_lib/sandbox/box.py
kyzylborda_lib/sandbox/environment.py
kyzylborda_lib/sandbox/health_checks.py
kyzylborda_lib/sandbox/readiness.py
kyzylborda_lib/sandbox/start.py
kyzylborda_lib/secrets/__init__.py
kyzylborda_lib/secrets/autodetect.py
kyzylborda_lib/secrets/default_generator.py
kyzylborda_lib/secrets/encoding.py
kyzylborda_lib/secrets/patterns.py
kyzylborda_lib/server/__init__.py
kyzylborda_lib/server/__main__.py
kyzylborda_lib/server/address.py
kyzylborda_lib/server/handlers.py
kyzylborda_lib/server/http/__init__.py
kyzylborda_lib/server/http/connection.py
kyzylborda_lib/server/http/pre_handler.py
kyzylborda_lib/server/http/protocol_commons.py
kyzylborda_lib/server/http/request.py
kyzylborda_lib/server/http/response.py
kyzylborda_lib/server/tcp/__init__.py
kyzylborda_lib/server/tcp/bridge.py
kyzylborda_lib/server/tcp/connection.py
kyzylborda_lib/server/tcp/reverse_proxy.py
kyzylborda_lib/server/telnet/__init__.py
kyzylborda_lib/server/telnet/bridge.py
kyzylborda_lib/server/telnet/commands.py
kyzylborda_lib/server/telnet/connection.py
kyzylborda_lib/server/udp/__init__.py
kyzylborda_lib/server/udp/bridge.py
kyzylborda_lib/server/udp/connection.py
kyzylborda_lib/server/udp/reverse_proxy.py
kyzylborda_lib-1.0.12.dist-info/METADATA
kyzylborda_lib-1.0.12.dist-info/WHEEL
kyzylborda_lib-1.0.12.dist-info/top_level.txt
kyzylborda_lib-1.0.12.dist-info/RECORD
