Metadata-Version: 2.2
Name: kyzylborda_lib
Version: 1.0.12
Requires-Dist: asyncinotify>=2.0.5
Requires-Dist: braceexpand>=0.1.7
Requires-Dist: python-magic>=0.4.27
Requires-Dist: PyYAML>=6.0
Requires-Dist: sortedcontainers>=2.4.0
